{"id":15833674,"pseudo":"Spiderman","online":true,"sex":1,"$ref":"http:\/\/www.adopteunmec.com\/api\/users\/15833674","age":27,"city":"Paris 2e","cover":"http:\/\/s4.adopteunmec.com\/fr\/4\/7\/6\/3\/3\/8\/5\/116","last_cnx":"2014-08-11 08:59:29","last_cnx_label":"en ligne","style":"0","in_contact":false,"points":120570,"birthdate":"1987-07-07","title":"Jolie temps pour les viagers...","zip":"75002","country":"fr","can_mail":false,"is_faked":false,"is_blocked":false,"in_basket":false,"pics":["http:\/\/s4.adopteunmec.com\/fr\/4\/7\/6\/3\/3\/8\/5\/106","http:\/\/s4.adopteunmec.com\/fr\/4\/7\/6\/3\/3\/8\/5\/116","http:\/\/s4.adopteunmec.com\/fr\/4\/7\/6\/3\/3\/8\/5\/118"],"hashtags":[{"id":9,"label":"cheveuxlongs"},{"id":29,"label":"bio"},{"id":1010,"label":"spiderman"},{"id":1358,"label":"paris2"},{"id":20,"label":"yeuxverts"},{"id":1143,"label":"globetrotter"},{"id":104,"label":"bonbon"}],"job":"Spiderman","music":[],"cinema":[],"books":[],"tvs":[],"hobbies":"","fall_for":"","turned_on_by":"quand je vais au salon de la caravane","cant_stand":"Le type \u00e9tait pas tr\u00e8s poli, alors je lui dit, attention, la petite souris va passer...","vices":"","fantasies":" Vous vous la racontez mais y'a pas si longtemps, vous dansiez tous la tecktonik.","assets":"","size":"165","weight":"50","shape":"6","origins":"1","hair_size":"4","hair_color":"5","eyes_color":"5","tobacco":"2","alcohol":"1","diet":"5","features":[],"character":[],"arousing":[],"sexgames":[],"sextoys":[],"underwear":[],"about1":"On est plein dans ma t\u00eate mais c'est moi le chef !!!","about2":" \u003Cbr\u003EREGLE N*1 : Quand tu portes un legging en imprim\u00e9 animal, peser moins lourd que l'animal en question \u003Cbr\u003E\u003Cbr\u003EREGLE N*2 : Les gens qui \"croivent que c'qui voyent\"...  Allez tous mourir !\u003Cbr\u003E\u003Cbr\u003E\u003Cbr\u003E------------\u003Cbr\u003E\u003Cbr\u003E\u003Cbr\u003E\u003Cbr\u003EJ'attends qu'on me fasse le rappel avant que ma voix soit r\u00e9-\u00e9teinte","styles":[],"favourite_food":["1"],"hair_style":"0","university":"","working":"1","announce":"On est plein dans ma t\u00eate mais c'est moi le chef !!!","shopping_list":" \nREGLE N*1 : Quand tu portes un legging en imprim\u00e9 animal, peser moins lourd que l'animal en question \n\nREGLE N*2 : Les gens qui \"croivent que c'qui voyent\"...  Allez tous mourir !\n\n\n------------\n\n\n\nJ'attends qu'on me fasse le rappel avant que ma voix soit r\u00e9-\u00e9teinte","enabled_badges":[{"id":18,"level":1},{"id":19,"level":2},{"id":20,"level":1},{"id":21,"level":2},{"id":22,"level":2},{"id":26,"level":1},{"id":27,"level":1},{"id":28,"level":1},{"id":32,"level":3},{"id":40,"level":3},{"id":42,"level":1},{"id":46,"level":1},{"id":47,"level":1},{"id":48,"level":1}],"disabled_badges":[]}