{"id":19415105,"pseudo":"Kar","online":true,"sex":1,"$ref":"http:\/\/www.adopteunmec.com\/api\/users\/19415105","age":25,"city":"Paris 11e","cover":"http:\/\/s5.adopteunmec.com\/fr\/5\/0\/1\/5\/1\/4\/9\/18","last_cnx":"2014-08-11 08:59:43","last_cnx_label":"en ligne","styles":["2","3","13"],"in_contact":false,"points":68310,"birthdate":"1989-02-12","title":"","zip":"75011","country":"fr","can_mail":false,"is_faked":false,"is_blocked":false,"in_basket":false,"pics":["http:\/\/s5.adopteunmec.com\/fr\/5\/0\/1\/5\/1\/4\/9\/12","http:\/\/s5.adopteunmec.com\/fr\/5\/0\/1\/5\/1\/4\/9\/16","http:\/\/s5.adopteunmec.com\/fr\/5\/0\/1\/5\/1\/4\/9\/18"],"hashtags":[{"id":9,"label":"cheveuxlongs"},{"id":120,"label":"etudiante"},{"id":189,"label":"natation"},{"id":70,"label":"bcbg"},{"id":491,"label":"amywinehouse"},{"id":1117,"label":"wesanderson"},{"id":1367,"label":"paris11"},{"id":71,"label":"chic"},{"id":310,"label":"thexx"},{"id":499,"label":"quentintarantino"}],"job":"Etudiante","music":["The XX","Ella Fitzgerald","Amy Winehouse","..."],"cinema":["Peter Greenaway","Wes Anderson","Quentin Tarantino","..."],"books":["Murakami Haruki","Colette ","Peter Mayle ","..."],"tvs":["Hannibal","Nurse Jackie  ","Boston Legal ","..."],"hobbies":"Natation","fall_for":"","turned_on_by":"","cant_stand":"","vices":"","fantasies":"","assets":"","size":"165","weight":"50","shape":"3","origins":"4","hair_size":"4","hair_color":"3","eyes_color":"1","tobacco":"2","alcohol":"2","diet":"1","features":[],"character":[],"arousing":[],"sexgames":[],"sextoys":[],"underwear":[],"about1":"I am here for my curiosity, and I have insomnia these days. Since I have time at night, why not? \u003Cbr\u003E\u003Cbr\u003EAnd what I need to tell is I hate to take photos! Sorry, in this way, I am not a typical Asian girl ;) Don't ask me for other pics. I know who I am, and I will be more charming if we have the chance to see each other in the real life. \u003Cbr\u003E\u003Cbr\u003EI consider myself as girl-child, will be always curious about everything (yes, I am an international student, to be here, it is already my adventure), be happy and willing to learn.\u003Cbr\u003E\u003Cbr\u003ESome boys consider I am cute, some think I am sexy, you guys have different standards, I can't tell. Everything is just a feeling, it is what about an attraction:  physical and spiritual. \u003Cbr\u003E\u003Cbr\u003EWhat is going next? We will see.\u003Cbr\u003E\u003Cbr\u003EI am tried, I'd better go.","about2":"I don't have a type, if I like you, I like you.\u003Cbr\u003EVice versa.\u003Cbr\u003ECome as you are.","favourite_food":[],"hair_style":"1","university":"","working":"2","announce":"I am here for my curiosity, and I have insomnia these days. Since I have time at night, why not? \n\nAnd what I need to tell is I hate to take photos! Sorry, in this way, I am not a typical Asian girl ;) Don't ask me for other pics. I know who I am, and I will be more charming if we have the chance to see each other in the real life. \n\nI consider myself as girl-child, will be always curious about everything (yes, I am an international student, to be here, it is already my adventure), be happy and willing to learn.\n\nSome boys consider I am cute, some think I am sexy, you guys have different standards, I can't tell. Everything is just a feeling, it is what about an attraction:  physical and spiritual. \n\nWhat is going next? We will see.\n\nI am tried, I'd better go.","shopping_list":"I don't have a type, if I like you, I like you.\nVice versa.\nCome as you are.","enabled_badges":[{"id":18,"level":1},{"id":19,"level":1},{"id":20,"level":1},{"id":22,"level":1},{"id":26,"level":1},{"id":28,"level":1},{"id":36,"level":1},{"id":38,"level":1},{"id":40,"level":3},{"id":42,"level":1},{"id":46,"level":1},{"id":47,"level":1},{"id":48,"level":1}],"disabled_badges":[]}